notebook_environments.py
notebook_environments-0.8.14.dist-info/LICENSE
notebook_environments-0.8.14.dist-info/METADATA
notebook_environments-0.8.14.dist-info/WHEEL
notebook_environments-0.8.14.dist-info/top_level.txt
notebook_environments-0.8.14.dist-info/RECORD
