Metadata-Version: 2.1
Name: notebook-environments
Version: 0.8.14
Summary: Manage python virtual environments on the working notebook server
Home-page: https://github.com/vladpunko/notebook-environments
Author: Vladislav Punko
Author-email: iam.vlad.punko@gmail.com
License: MIT
Project-URL: Issue tracker, https://github.com/vladpunko/notebook-environments/issues
Project-URL: Source code, https://github.com/vladpunko/notebook-environments
Platform: macOS
Platform: POSIX
Classifier: Intended Audience :: Developers
Classifier: Intended Audience :: Science/Research
Classifier: Intended Audience :: System Administrators
Classifier: License :: OSI Approved :: MIT License
Classifier: Operating System :: MacOS :: MacOS X
Classifier: Operating System :: POSIX
Classifier: Programming Language :: Python :: 2
Classifier: Programming Language :: Python :: 2.7
Classifier: Programming Language :: Python :: 3
Classifier: Programming Language :: Python :: 3.5
Classifier: Programming Language :: Python :: 3.6
Classifier: Programming Language :: Python :: 3.7
Classifier: Programming Language :: Python :: 3.8
Classifier: Programming Language :: Python :: 3.9
Classifier: Programming Language :: Python :: 3.10
Classifier: Programming Language :: Python :: 3.11
Classifier: Programming Language :: Python :: 3.12
Classifier: Topic :: Software Development :: Libraries :: Python Modules
Classifier: Topic :: Utilities
Requires-Python: >=2.7
License-File: LICENSE
